faebryk_core_cpp.cpython-312-x86_64-linux-gnu.so
faebryk-4.1.2.dist-info/RECORD
faebryk-4.1.2.dist-info/entry_points.txt
faebryk-4.1.2.dist-info/METADATA
faebryk-4.1.2.dist-info/WHEEL
faebryk-4.1.2.dist-info/licenses/LICENSE
faebryk/libs/iso_metric_screw_thread.py
faebryk/libs/algorithm.py
faebryk/libs/units.py
faebryk/libs/exceptions.py
faebryk/libs/util.py
faebryk/libs/font.py
faebryk/libs/logging.py
faebryk/libs/e_series.py
faebryk/libs/pycodegen.py
faebryk/libs/brightness.py
faebryk/libs/picker/common.py
faebryk/libs/picker/util.py
faebryk/libs/picker/lcsc.py
faebryk/libs/picker/picker.py
faebryk/libs/picker/jlcpcb/pickers.py
faebryk/libs/picker/jlcpcb/picker_lib.py
faebryk/libs/picker/jlcpcb/jlcpcb.py
faebryk/libs/picker/api/pickers.py
faebryk/libs/picker/api/picker_lib.py
faebryk/libs/picker/api/api.py
faebryk/libs/kicad/fileformats_common.py
faebryk/libs/kicad/fileformats.py
faebryk/libs/kicad/fileformats_sch.py
faebryk/libs/kicad/fileformats_v5.py
faebryk/libs/kicad/fileformats_version.py
faebryk/libs/kicad/paths.py
faebryk/libs/test/times.py
faebryk/libs/examples/pickers.py
faebryk/libs/examples/buildutil.py
faebryk/libs/examples/resources/example/example.kicad_pro
faebryk/libs/examples/resources/example/fp-lib-table
faebryk/libs/examples/resources/example/example.kicad_pcb
faebryk/libs/geometry/basic.py
faebryk/libs/tools/typer.py
faebryk/libs/sexp/util.py
faebryk/libs/sexp/dataclass_sexp.py
faebryk/libs/app/designators.py
faebryk/libs/app/parameters.py
faebryk/libs/app/kicad_netlist.py
faebryk/libs/app/manufacturing.py
faebryk/libs/app/checks.py
faebryk/libs/app/erc.py
faebryk/libs/app/pcb.py
faebryk/libs/library/L.py
faebryk/exporters/esphome/esphome.py
faebryk/exporters/pcb/kicad/transformer.py
faebryk/exporters/pcb/kicad/artifacts.py
faebryk/exporters/pcb/kicad/pcb.py
faebryk/exporters/pcb/routing/grid.py
faebryk/exporters/pcb/routing/util.py
faebryk/exporters/pcb/routing/README.md
faebryk/exporters/pcb/routing/routing.py
faebryk/exporters/pcb/layout/typehierarchy.py
faebryk/exporters/pcb/layout/next_to.py
faebryk/exporters/pcb/layout/heuristic_decoupling.py
