Metadata-Version: 2.3
Name: faebryk
Version: 4.1.2
Summary: Open-source software-defined EDA
Project-URL: Homepage, https://github.com/atopile/faebryk
Project-URL: Bug Tracker, https://github.com/atopile/faebryk/issues
Author-email: Ioannis Papamanoglou <ioannis@atopile.io>
License: MIT License
License-File: LICENSE
Classifier: License :: OSI Approved :: MIT License
Classifier: Operating System :: OS Independent
Classifier: Programming Language :: Python :: 3
Requires-Python: <3.13,>=3.12
Requires-Dist: black~=24.4.2
Requires-Dist: dataclasses-json~=0.6.7
Requires-Dist: deprecated~=1.2.14
Requires-Dist: easyeda2kicad~=0.8.0
Requires-Dist: freetype-py~=2.4.0
Requires-Dist: isort~=5.6.4
Requires-Dist: kicadcliwrapper~=1.0.0
Requires-Dist: matplotlib~=3.7.1
Requires-Dist: more-itertools~=10.4.0
Requires-Dist: networkx==3.3
Requires-Dist: numpy<3.0.0,>=1.24.3
Requires-Dist: patool~=2.3.0
Requires-Dist: pint~=0.24.3
Requires-Dist: psutil~=6.0.0
Requires-Dist: requests~=2.32.3
Requires-Dist: rich~=13.7.1
Requires-Dist: ruff<0.7.0,>=0.6.4
Requires-Dist: scipy<=1.14.0,>=1.11.1
Requires-Dist: sexpdata==1.0.2
Requires-Dist: shapely~=2.0.1
Requires-Dist: tortoise-orm~=0.21.3
Requires-Dist: typer<0.13,>=0.12
Requires-Dist: typing-extensions~=4.6.3
Provides-Extra: dev
Requires-Dist: dash-cytoscape~=1.0.2; extra == 'dev'
Requires-Dist: dash~=2.18.1; extra == 'dev'
Requires-Dist: gprof2dot~=2024.6.6; extra == 'dev'
Requires-Dist: pre-commit<4.0,>=2.20; extra == 'dev'
Requires-Dist: pybind11~=2.11.1; extra == 'dev'
Requires-Dist: pyinstrument~=4.7.1; extra == 'dev'
Requires-Dist: pytest-xdist~=3.6.1; extra == 'dev'
Requires-Dist: pytest<9.0.0,>=7.1.3; extra == 'dev'
Requires-Dist: viztracer~=0.16.3; extra == 'dev'
Provides-Extra: test
Requires-Dist: pybind11~=2.11.1; extra == 'test'
Requires-Dist: pytest-xdist~=3.6.1; extra == 'test'
Requires-Dist: pytest<9.0.0,>=7.1.3; extra == 'test'
